{
  "id": "charcot-marie-tooth_disease,_axonal,_type_2n",
  "subject": {
    "id": "patient1"
  },
  "phenotypicFeatures": [
    {
      "type": {
        "id": "HP:0009027",
        "label": "Foot dorsiflexor weakness"
      }
    },
    {
      "type": {
        "id": "HP:0003202",
        "label": "Skeletal muscle atrophy"
      }
    },
    {
      "type": {
        "id": "HP:0008944",
        "label": "Distal lower limb amyotrophy"
      }
    },
    {
      "type": {
        "id": "HP:0000407",
        "label": "Sensorineural hearing impairment"
      }
    },
    {
      "type": {
        "id": "HP:0002460",
        "label": "Distal muscle weakness"
      }
    },
    {
      "type": {
        "id": "HP:0012638",
        "label": "Abnormal nervous system physiology"
      }
    },
    {
      "type": {
        "id": "HP:0031004",
        "label": "Hemiareflexia"
      }
    }
  ],
  "diseases": [
    {
      "term": {
        "id": "OMIM:613287",
        "label": "Charcot-Marie-Tooth disease, axonal, type 2N"
      }
    }
  ],
  "metaData": {
    "created": "2024-06-11T19:05:36.551773Z",
    "createdBy": "phenotype2phenopacket",
    "resources": [
      {
        "id": "hp",
        "name": "human phenotype ontology",
        "url": "http://purl.obolibrary.org/obo/hp.owl",
        "version": "hp/releases/2024-04-24",
        "namespacePrefix": "HP",
        "iriPrefix": "http://purl.obolibrary.org/obo/HP_"
      },
      {
        "id": "omim",
        "name": "Online Mendelian Inheritance in Man",
        "url": "https://www.omim.org",
        "version": "hp/releases/2023-04-18",
        "namespacePrefix": "OMIM",
        "iriPrefix": "https://omim.org/entry/"
      }
    ],
    "phenopacketSchemaVersion": "2.0"
  }
}