{
  "id": "craniofacial_dysmorphism,_skeletal_anomalies,_and_impaired_intellectual_development_syndrome_2",
  "subject": {
    "id": "patient1"
  },
  "phenotypicFeatures": [
    {
      "type": {
        "id": "HP:0012368",
        "label": "Flat face"
      }
    },
    {
      "type": {
        "id": "HP:0000368",
        "label": "Low-set, posteriorly rotated ears"
      }
    },
    {
      "type": {
        "id": "HP:0001344",
        "label": "Absent speech"
      }
    },
    {
      "type": {
        "id": "HP:0000765",
        "label": "Abnormal thorax morphology"
      }
    },
    {
      "type": {
        "id": "HP:0000915",
        "label": "Pectus excavatum of inferior sternum"
      }
    },
    {
      "type": {
        "id": "HP:5201014",
        "label": "Asymmetric bilateral cleft lip"
      }
    }
  ],
  "diseases": [
    {
      "term": {
        "id": "OMIM:616994",
        "label": "Craniofacial dysmorphism, skeletal anomalies, and impaired intellectual development syndrome 2"
      }
    }
  ],
  "metaData": {
    "created": "2024-06-11T20:13:16.443936Z",
    "createdBy": "phenotype2phenopacket",
    "resources": [
      {
        "id": "hp",
        "name": "human phenotype ontology",
        "url": "http://purl.obolibrary.org/obo/hp.owl",
        "version": "hp/releases/2024-04-24",
        "namespacePrefix": "HP",
        "iriPrefix": "http://purl.obolibrary.org/obo/HP_"
      },
      {
        "id": "omim",
        "name": "Online Mendelian Inheritance in Man",
        "url": "https://www.omim.org",
        "version": "hp/releases/2023-04-18",
        "namespacePrefix": "OMIM",
        "iriPrefix": "https://omim.org/entry/"
      }
    ],
    "phenopacketSchemaVersion": "2.0"
  }
}