{
  "id": "factor_v_excess_with_spontaneous_thrombosis",
  "subject": {
    "id": "patient1"
  },
  "phenotypicFeatures": [
    {
      "type": {
        "id": "HP:0004950",
        "label": "Peripheral arterial stenosis"
      }
    },
    {
      "type": {
        "id": "HP:0011996",
        "label": "Elevated coagulation factor V activity"
      }
    }
  ],
  "diseases": [
    {
      "term": {
        "id": "OMIM:134400",
        "label": "Factor V excess with spontaneous thrombosis"
      }
    }
  ],
  "metaData": {
    "created": "2024-06-11T20:48:15.549062Z",
    "createdBy": "phenotype2phenopacket",
    "resources": [
      {
        "id": "hp",
        "name": "human phenotype ontology",
        "url": "http://purl.obolibrary.org/obo/hp.owl",
        "version": "hp/releases/2024-04-24",
        "namespacePrefix": "HP",
        "iriPrefix": "http://purl.obolibrary.org/obo/HP_"
      },
      {
        "id": "omim",
        "name": "Online Mendelian Inheritance in Man",
        "url": "https://www.omim.org",
        "version": "hp/releases/2023-04-18",
        "namespacePrefix": "OMIM",
        "iriPrefix": "https://omim.org/entry/"
      }
    ],
    "phenopacketSchemaVersion": "2.0"
  }
}