{
  "id": "humerofemoral_hypoplasia_with_radiotibial_ray_deficiency",
  "subject": {
    "id": "patient1"
  },
  "phenotypicFeatures": [
    {
      "type": {
        "id": "HP:0000882",
        "label": "Hypoplastic scapulae"
      }
    },
    {
      "type": {
        "id": "HP:0002996",
        "label": "Limited elbow movement"
      }
    },
    {
      "type": {
        "id": "HP:0011842",
        "label": "Abnormal skeletal morphology"
      }
    },
    {
      "type": {
        "id": "HP:0005927",
        "label": "Aplasia/hypoplasia involving bones of the hand"
      }
    },
    {
      "type": {
        "id": "HP:0002057",
        "label": "Prominent glabella"
      }
    },
    {
      "type": {
        "id": "HP:0001883",
        "label": "Talipes"
      }
    },
    {
      "type": {
        "id": "HP:0000308",
        "label": "Microretrognathia"
      }
    }
  ],
  "diseases": [
    {
      "term": {
        "id": "OMIM:618022",
        "label": "Humerofemoral hypoplasia with radiotibial ray deficiency"
      }
    }
  ],
  "metaData": {
    "created": "2024-06-11T21:48:40.524483Z",
    "createdBy": "phenotype2phenopacket",
    "resources": [
      {
        "id": "hp",
        "name": "human phenotype ontology",
        "url": "http://purl.obolibrary.org/obo/hp.owl",
        "version": "hp/releases/2024-04-24",
        "namespacePrefix": "HP",
        "iriPrefix": "http://purl.obolibrary.org/obo/HP_"
      },
      {
        "id": "omim",
        "name": "Online Mendelian Inheritance in Man",
        "url": "https://www.omim.org",
        "version": "hp/releases/2023-04-18",
        "namespacePrefix": "OMIM",
        "iriPrefix": "https://omim.org/entry/"
      }
    ],
    "phenopacketSchemaVersion": "2.0"
  }
}