{
  "id": "robinow-sorauf_syndrome",
  "subject": {
    "id": "patient1"
  },
  "phenotypicFeatures": [
    {
      "type": {
        "id": "HP:0003189",
        "label": "Long nose"
      }
    },
    {
      "type": {
        "id": "HP:0001822",
        "label": "Hallux valgus"
      }
    },
    {
      "type": {
        "id": "HP:0000460",
        "label": "Narrow nose"
      }
    },
    {
      "type": {
        "id": "HP:0010055",
        "label": "Broad hallux"
      }
    },
    {
      "type": {
        "id": "HP:0011304",
        "label": "Broad thumb"
      }
    },
    {
      "type": {
        "id": "HP:0000494",
        "label": "Downslanted palpebral fissures"
      }
    },
    {
      "type": {
        "id": "HP:0007911",
        "label": "Congenital bilateral ptosis"
      }
    },
    {
      "type": {
        "id": "HP:0000549",
        "label": "Abnormal conjugate eye movement"
      }
    }
  ],
  "diseases": [
    {
      "term": {
        "id": "OMIM:180750",
        "label": "Robinow-Sorauf syndrome"
      }
    }
  ],
  "metaData": {
    "created": "2024-06-11T21:05:51.302034Z",
    "createdBy": "phenotype2phenopacket",
    "resources": [
      {
        "id": "hp",
        "name": "human phenotype ontology",
        "url": "http://purl.obolibrary.org/obo/hp.owl",
        "version": "hp/releases/2024-04-24",
        "namespacePrefix": "HP",
        "iriPrefix": "http://purl.obolibrary.org/obo/HP_"
      },
      {
        "id": "omim",
        "name": "Online Mendelian Inheritance in Man",
        "url": "https://www.omim.org",
        "version": "hp/releases/2023-04-18",
        "namespacePrefix": "OMIM",
        "iriPrefix": "https://omim.org/entry/"
      }
    ],
    "phenopacketSchemaVersion": "2.0"
  }
}