{
  "id": "stickler_syndrome,_type_v",
  "subject": {
    "id": "patient1"
  },
  "phenotypicFeatures": [
    {
      "type": {
        "id": "HP:0011800",
        "label": "Midface retrusion"
      }
    },
    {
      "type": {
        "id": "HP:0004327",
        "label": "Abnormal vitreous humor morphology"
      }
    },
    {
      "type": {
        "id": "HP:0000545",
        "label": "Myopia"
      }
    },
    {
      "type": {
        "id": "HP:0000479",
        "label": "Abnormal retinal morphology"
      }
    },
    {
      "type": {
        "id": "HP:0000331",
        "label": "Short chin"
      }
    }
  ],
  "diseases": [
    {
      "term": {
        "id": "OMIM:614284",
        "label": "Stickler syndrome, type V"
      }
    }
  ],
  "metaData": {
    "created": "2024-06-11T23:38:34.756598Z",
    "createdBy": "phenotype2phenopacket",
    "resources": [
      {
        "id": "hp",
        "name": "human phenotype ontology",
        "url": "http://purl.obolibrary.org/obo/hp.owl",
        "version": "hp/releases/2024-04-24",
        "namespacePrefix": "HP",
        "iriPrefix": "http://purl.obolibrary.org/obo/HP_"
      },
      {
        "id": "omim",
        "name": "Online Mendelian Inheritance in Man",
        "url": "https://www.omim.org",
        "version": "hp/releases/2023-04-18",
        "namespacePrefix": "OMIM",
        "iriPrefix": "https://omim.org/entry/"
      }
    ],
    "phenopacketSchemaVersion": "2.0"
  }
}