{
  "id": "thoracoabdominal_syndrome",
  "subject": {
    "id": "patient1"
  },
  "phenotypicFeatures": [
    {
      "type": {
        "id": "HP:0000175",
        "label": "Cleft palate"
      }
    },
    {
      "type": {
        "id": "HP:0002323",
        "label": "Anencephaly"
      }
    },
    {
      "type": {
        "id": "HP:0030680",
        "label": "Abnormal cardiovascular system morphology"
      }
    },
    {
      "type": {
        "id": "HP:0002933",
        "label": "Ventral hernia"
      }
    },
    {
      "type": {
        "id": "HP:5201001",
        "label": "Complete unilateral cleft lip"
      }
    },
    {
      "type": {
        "id": "HP:0000776",
        "label": "Congenital diaphragmatic hernia"
      }
    },
    {
      "type": {
        "id": "HP:0001539",
        "label": "Omphalocele"
      }
    }
  ],
  "diseases": [
    {
      "term": {
        "id": "OMIM:313850",
        "label": "Thoracoabdominal syndrome"
      }
    }
  ],
  "metaData": {
    "created": "2024-06-11T19:18:27.268637Z",
    "createdBy": "phenotype2phenopacket",
    "resources": [
      {
        "id": "hp",
        "name": "human phenotype ontology",
        "url": "http://purl.obolibrary.org/obo/hp.owl",
        "version": "hp/releases/2024-04-24",
        "namespacePrefix": "HP",
        "iriPrefix": "http://purl.obolibrary.org/obo/HP_"
      },
      {
        "id": "omim",
        "name": "Online Mendelian Inheritance in Man",
        "url": "https://www.omim.org",
        "version": "hp/releases/2023-04-18",
        "namespacePrefix": "OMIM",
        "iriPrefix": "https://omim.org/entry/"
      }
    ],
    "phenopacketSchemaVersion": "2.0"
  }
}